hpf/__init__.py
hpf/__main__.py
hpf-0.3.14.1.dist-info/licenses/LICENSE
hpf-0.3.14.1.dist-info/METADATA
hpf-0.3.14.1.dist-info/WHEEL
hpf-0.3.14.1.dist-info/top_level.txt
hpf-0.3.14.1.dist-info/RECORD
