Metadata-Version: 2.4
Name: hpf
Version: 0.3.14.1
Summary: A high precision floating-point arithmetic module
Home-page: https://github.com/zprolab/hpf
Author: Chenyun Zhang
Author-email: "Chenyun Z." <zcy@hi-zcy.com>
License: BSD-3-Clause
Keywords: math
Classifier: License :: OSI Approved :: MIT License
Classifier: Programming Language :: Python :: 3
Classifier: Programming Language :: Python :: 3.9
Classifier: Programming Language :: Python :: 3.10
Classifier: Programming Language :: Python :: 3.11
Classifier: Programming Language :: Python :: 3.12
Classifier: Programming Language :: Python :: 3.13
Requires-Python: >=3.0
License-File: LICENSE
Dynamic: author
Dynamic: home-page
Dynamic: license-file
Dynamic: requires-python
